interceptorator/__init__.py
interceptorator/decorator.py
interceptorator/generics.py
interceptorator/storage/__init__.py
interceptorator/storage/sqllite3.py
interceporaptor-0.0.1.dev1.dist-info/METADATA
interceporaptor-0.0.1.dev1.dist-info/WHEEL
interceporaptor-0.0.1.dev1.dist-info/top_level.txt
interceporaptor-0.0.1.dev1.dist-info/RECORD
