Metadata-Version: 2.1
Name: interceporaptor
Version: 0.0.1.dev1
Summary: Intercept banana environment data (a.k.a. another VCR.py)
License: MIT License
Classifier: Intended Audience :: Developers
Classifier: Operating System :: OS Independent
Classifier: Programming Language :: Python
Classifier: Programming Language :: Python :: 3
Classifier: Topic :: Software Development :: Debuggers
Classifier: Topic :: Software Development :: Quality Assurance
Classifier: Topic :: Software Development :: Testing
